Script/__init__.py
Script/main.py
Script/Graph/__init__.py
Script/Graph/plot.py
Script/Report/__init__.py
Script/Report/model.py
Edatora-0.2.dist-info/LICENSE
Edatora-0.2.dist-info/METADATA
Edatora-0.2.dist-info/WHEEL
Edatora-0.2.dist-info/top_level.txt
Edatora-0.2.dist-info/RECORD
